youart/__init__.py
youart/arguments.py
youart/cli.py
youart/logger.py
youart/release.py
youart/screen.py
youart/utils.py
youart-0.0.2.dist-info/METADATA
youart-0.0.2.dist-info/WHEEL
youart-0.0.2.dist-info/entry_points.txt
youart-0.0.2.dist-info/top_level.txt
youart-0.0.2.dist-info/RECORD
