Metadata-Version: 2.1
Name: youart
Version: 0.0.2
Summary: monitor and save UART logs
Home-page: http://gitlab.com/7aman/youart
Author: Zaman
Author-email: 7amaaan@gmail.com
License: MIT
Project-URL: source, http://gitlab.com/7aman/youart
Keywords: UART serial
Classifier: Programming Language :: Python :: 3 :: Only
Classifier: Development Status :: 5 - Production/Stable
Classifier: Environment :: Console
Classifier: Intended Audience :: End Users/Desktop
Classifier: License :: OSI Approved :: MIT License
Classifier: Natural Language :: English
Classifier: Topic :: Utilities
Requires-Python: >=3.7
Requires-Dist: pyserial
